{
  "generated_at": "2026-06-18T20:57:08.140389+08:00",
  "total_titles_processed": 1144,
  "failed_sources": [],
  "trends": [
    {
      "keyword_group": "特朗普 马斯克 加密货币 美联储",
      "match_count": 93,
      "titles": [
        {
          "title": "美联储继续按兵不动但暗示鹰派倾向，强调通胀承诺，半数决策者料年内加息",
          "url": "https://wallstreetcn.com/articles/3774938",
          "source": "华尔街见闻",
          "ranks": [
            7,
            5,
            3
          ],
          "is_new": false,
          "appearance_count": 7,
          "time_info": "[05时10分 ~ 20时57分]"
        },
        {
          "title": "今夜全球瞩目，沃什“美联储首秀”会向市场扔炸弹吗？",
          "url": "https://wallstreetcn.com/articles/3774886",
          "source": "华尔街见闻",
          "ranks": [
            1,
            4
          ],
          "is_new": false,
          "appearance_count": 5,
          "time_info": "[02时23分 ~ 12时15分]"
        },
        {
          "title": "美联储按兵不动但释放鹰派信号 年内利率变化预期由降息变加息",
          "url": "https://www.cls.cn/detail/2402931",
          "source": "财联社热门",
          "ranks": [
            2,
            1
          ],
          "is_new": false,
          "appearance_count": 4,
          "time_info": "[05时10分 ~ 12时15分]"
        },
        {
          "title": "完整版首秀问答！美联储主席沃什：坚守2%通胀目标，成立五个特别工作组，个人未提交点阵图",
          "url": "https://wallstreetcn.com/articles/3774941",
          "source": "华尔街见闻",
          "ranks": [
            2
          ],
          "is_new": false,
          "appearance_count": 4,
          "time_info": "[12时15分 ~ 20时57分]"
        },
        {
          "title": "美伊协议“推手”曝光？特朗普坦言：我不想看到经济灾难、不想当胡佛！",
          "url": "https://www.cls.cn/detail/2403312",
          "source": "财联社热门",
          "ranks": [
            3,
            2
          ],
          "is_new": false,
          "appearance_count": 3,
          "time_info": "[17时17分 ~ 20时57分]"
        },
        {
          "title": "特朗普对记者大喊：我们签了，在凡尔赛宫里签的",
          "url": "https://v.ifeng.com/c/8u3B5EM0Jqc",
          "source": "凤凰网",
          "ranks": [
            4,
            3
          ],
          "is_new": false,
          "appearance_count": 2,
          "time_info": "[12时15分 ~ 17时17分]"
        },
        {
          "title": "特朗普：美联储按兵不动也还行，加息难以置信但可能发生，相信沃什",
          "url": "https://wallstreetcn.com/articles/3774946",
          "source": "华尔街见闻",
          "ranks": [
            6,
            5
          ],
          "is_new": false,
          "appearance_count": 4,
          "time_info": "[12时15分 ~ 20时57分]"
        },
        {
          "title": "美联储新主席沃什释放强烈信号：美联储的天，要变了",
          "url": "https://www.cls.cn/detail/2402978",
          "source": "财联社热门",
          "ranks": [
            4,
            5
          ],
          "is_new": false,
          "appearance_count": 2,
          "time_info": "[07时28分 ~ 12时15分]"
        },
        {
          "title": "特朗普：如果我不满意，将恢复向伊朗投掷炸弹",
          "url": "https://m.thepaper.cn/newsDetail_forward_33400508",
          "source": "澎湃新闻",
          "ranks": [
            13,
            14,
            8,
            7
          ],
          "is_new": false,
          "appearance_count": 6,
          "time_info": "[02时23分 ~ 17时17分]"
        },
        {
          "title": "标普500指数期货上涨0.5%，从美联储发布决议后的跌势中反弹。",
          "url": "https://wallstreetcn.com/livenews/3121300",
          "source": "华尔街见闻-快讯",
          "ranks": [
            1
          ],
          "is_new": false,
          "appearance_count": 1,
          "time_info": "07时28分"
        },
        {
          "title": "美联储宣布维持利率不变",
          "url": "https://www.douyin.com/hot/2538695",
          "source": "抖音",
          "ranks": [
            1
          ],
          "is_new": false,
          "appearance_count": 1,
          "time_info": "12时15分"
        },
        {
          "title": "特朗普：感谢中俄“完全中立”，让情况好转了很多",
          "url": "https://news.ifeng.com/c/8u3EpDjUAsS",
          "source": "凤凰网",
          "ranks": [
            2
          ],
          "is_new": false,
          "appearance_count": 1,
          "time_info": "17时17分"
        },
        {
          "title": "法兴银行美国研究负责人Rajappa：核心通胀将成为美联储的真正担忧。",
          "url": "https://flash.jin10.com/detail/20260618015207915800",
          "source": "金十数据",
          "ranks": [
            2
          ],
          "is_new": false,
          "appearance_count": 1,
          "time_info": "02时23分"
        },
        {
          "title": "摩根资产管理Michele：经济形势不适合降息，沃什注定让特朗普失望",
          "url": "https://wallstreetcn.com/livenews/3121178",
          "source": "华尔街见闻-快讯",
          "ranks": [
            2
          ],
          "is_new": false,
          "appearance_count": 1,
          "time_info": "02时23分"
        },
        {
          "title": "花旗集团：将美联储加息时间的预期推后一个月，至10月份。",
          "url": "https://wallstreetcn.com/livenews/3121257",
          "source": "华尔街见闻-快讯",
          "ranks": [
            2
          ],
          "is_new": false,
          "appearance_count": 1,
          "time_info": "05时11分"
        },
        {
          "title": "特朗普：我已经签署美伊谅解备忘录，我们在凡尔赛宫签署的。",
          "url": "https://wallstreetcn.com/livenews/3121299",
          "source": "华尔街见闻-快讯",
          "ranks": [
            2
          ],
          "is_new": false,
          "appearance_count": 1,
          "time_info": "07时28分"
        },
        {
          "title": "一图解读美联储6月决议：如期“按兵不动”，沃什明言重大改革将至！",
          "url": "https://www.cls.cn/detail/2403006",
          "source": "财联社热门",
          "ranks": [
            3
          ],
          "is_new": false,
          "appearance_count": 1,
          "time_info": "12时15分"
        },
        {
          "title": "提醒：北京时间02:00，美联储发布FOMC利率决议声明和经济预期概要（SEP，含利率预测点阵图）。",
          "url": "https://wallstreetcn.com/livenews/3121177",
          "source": "华尔街见闻-快讯",
          "ranks": [
            3
          ],
          "is_new": false,
          "appearance_count": 1,
          "time_info": "02时23分"
        },
        {
          "title": "香港金融管理局将基准利率维持在4%，隔夜美联储按兵不动。",
          "url": "https://wallstreetcn.com/livenews/3121297",
          "source": "华尔街见闻-快讯",
          "ranks": [
            4
          ],
          "is_new": false,
          "appearance_count": 1,
          "time_info": "07时28分"
        },
        {
          "title": "美联储维持利率不变有何影响",
          "url": "https://search.bilibili.com/all?keyword=%E7%BE%8E%E8%81%94%E5%82%A8%E7%BB%B4%E6%8C%81%E5%88%A9%E7%8E%87%E4%B8%8D%E5%8F%98%E6%9C%89%E4%BD%95%E5%BD%B1%E5%93%8D",
          "source": "bilibili 热搜",
          "ranks": [
            16,
            5,
            19
          ],
          "is_new": false,
          "appearance_count": 4,
          "time_info": "[12时15分 ~ 20时57分]"
        },
        {
          "title": "特朗普罕见批评以色列：不能每次为找一个人，炸掉整栋楼",
          "url": "https://news.ifeng.com/c/8u1h2zVfjEK",
          "source": "凤凰网",
          "ranks": [
            8
          ],
          "is_new": false,
          "appearance_count": 5,
          "time_info": "[02时23分 ~ 12时15分]"
        },
        {
          "title": "美联储利率决议前：本次会议维持利率不变的概率为99.6%",
          "url": "https://flash.jin10.com/detail/20260618015124632800",
          "source": "金十数据",
          "ranks": [
            5
          ],
          "is_new": false,
          "appearance_count": 1,
          "time_info": "02时23分"
        },
        {
          "title": "特朗普离开凡尔赛宫时说签署了伊朗备忘录",
          "url": "https://flash.jin10.com/detail/20260618071620986800",
          "source": "金十数据",
          "ranks": [
            5
          ],
          "is_new": false,
          "appearance_count": 1,
          "time_info": "07时28分"
        },
        {
          "title": "花旗：预计美联储将在2026年10月、12月和2027年1月各降息25个基点，此前预测为今年9月、10月和12月降息。",
          "url": "https://flash.jin10.com/detail/20260618113820055800",
          "source": "金十数据",
          "ranks": [
            5
          ],
          "is_new": false,
          "appearance_count": 1,
          "time_info": "12时15分"
        },
        {
          "title": "阿联酋总统太小声？特朗普当面调侃：像他那么有钱，确实不用大声",
          "url": "https://m.thepaper.cn/newsDetail_forward_33397131",
          "source": "澎湃新闻",
          "ranks": [
            14,
            15,
            10
          ],
          "is_new": false,
          "appearance_count": 5,
          "time_info": "[02时23分 ~ 12时15分]"
        },
        {
          "title": "“马克龙想借中国，来跟特朗普讨价还价”",
          "url": "https://news.ifeng.com/c/8u1zHWun1pQ",
          "source": "凤凰网",
          "ranks": [
            7
          ],
          "is_new": false,
          "appearance_count": 4,
          "time_info": "[02时23分 ~ 07时28分]"
        },
        {
          "title": "沃什“美联储首秀”来袭 SpaceX延续涨势 英特尔带动芯片股反弹 | 今夜看点",
          "url": "https://www.cls.cn/detail/2402766",
          "source": "财联社热门",
          "ranks": [
            7,
            8,
            9
          ],
          "is_new": false,
          "appearance_count": 4,
          "time_info": "[02时23分 ~ 07时28分]"
        },
        {
          "title": "美联储",
          "url": "https://s.weibo.com/weibo?q=%E7%BE%8E%E8%81%94%E5%82%A8&t=31&band_rank=7&Refer=top",
          "source": "微博",
          "ranks": [
            7,
            9
          ],
          "is_new": false,
          "appearance_count": 4,
          "time_info": "[02时23分 ~ 07时28分]"
        },
        {
          "title": "美联储内部鸽派集体转鹰，沃什首秀“左右为难”",
          "url": "https://wallstreetcn.com/articles/3774866",
          "source": "华尔街见闻",
          "ranks": [
            9
          ],
          "is_new": false,
          "appearance_count": 4,
          "time_info": "[02时23分 ~ 07时28分]"
        },
        {
          "title": "特朗普又炮轰内塔尼亚胡：没我，就没以色列",
          "url": "https://news.ifeng.com/c/8u1wV2q6hDQ",
          "source": "凤凰网",
          "ranks": [
            9
          ],
          "is_new": false,
          "appearance_count": 4,
          "time_info": "[02时23分 ~ 07时28分]"
        },
        {
          "title": "“特朗普这么干，又给中国打广告”",
          "url": "https://news.ifeng.com/c/8u2Dv7mxUaG",
          "source": "凤凰网",
          "ranks": [
            10
          ],
          "is_new": false,
          "appearance_count": 4,
          "time_info": "[02时23分 ~ 07时28分]"
        },
        {
          "title": "美官员称特朗普亲自签署美伊谅解备忘录",
          "url": "https://m.thepaper.cn/newsDetail_forward_33404444",
          "source": "澎湃新闻",
          "ranks": [
            17,
            14,
            11
          ],
          "is_new": false,
          "appearance_count": 4,
          "time_info": "[12时15分 ~ 20时57分]"
        },
        {
          "title": "为美伊协议辩护，特朗普称“不想看到经济灾难”，不想做“导致1929年崩盘的胡佛”",
          "url": "https://wallstreetcn.com/articles/3774952",
          "source": "华尔街见闻",
          "ranks": [
            6,
            7
          ],
          "is_new": false,
          "appearance_count": 3,
          "time_info": "[17时17分 ~ 20时57分]"
        },
        {
          "title": "美学者：特朗普凡尔赛签约离谱至极",
          "url": "https://news.ifeng.com/c/8u3ct1grAdS",
          "source": "凤凰网",
          "ranks": [
            8,
            11
          ],
          "is_new": false,
          "appearance_count": 3,
          "time_info": "[17时17分 ~ 20时57分]"
        },
        {
          "title": "仅132字！沃什大幅调整美联储利率声明，全文对比美联储6月会议声明有何变化",
          "url": "https://wallstreetcn.com/articles/3774940",
          "source": "华尔街见闻",
          "ranks": [
            10,
            9
          ],
          "is_new": false,
          "appearance_count": 3,
          "time_info": "[17时17分 ~ 20时57分]"
        },
        {
          "title": "特朗普：谅解备忘录不是最终协议 若不满意会重新开火",
          "url": "https://www.cls.cn/detail/2402714",
          "source": "财联社热门",
          "ranks": [
            12,
            13
          ],
          "is_new": false,
          "appearance_count": 3,
          "time_info": "[02时23分 ~ 05时11分]"
        },
        {
          "title": "特朗普：高市早苗是我的头号粉丝，不信你问她",
          "url": "https://m.thepaper.cn/newsDetail_forward_33405392",
          "source": "澎湃新闻",
          "ranks": [
            18,
            15
          ],
          "is_new": false,
          "appearance_count": 3,
          "time_info": "[17时17分 ~ 20时57分]"
        },
        {
          "title": "特朗普G7峰会迟到，还宣布“我是老大”",
          "url": "https://news.ifeng.com/c/8u3Bdreuuj0",
          "source": "凤凰网",
          "ranks": [
            9,
            7
          ],
          "is_new": false,
          "appearance_count": 2,
          "time_info": "[12时15分 ~ 17时17分]"
        },
        {
          "title": "特朗普：欧洲承诺参与霍尔木兹海峡扫雷",
          "url": "https://news.ifeng.com/c/8u3AtJ60oqA",
          "source": "凤凰网",
          "ranks": [
            7,
            12
          ],
          "is_new": false,
          "appearance_count": 2,
          "time_info": "[12时15分 ~ 17时17分]"
        },
        {
          "title": "特朗普在G7记者会说了什么",
          "url": "https://search.bilibili.com/all?keyword=%E7%89%B9%E6%9C%97%E6%99%AE%E5%9C%A8G7%E8%AE%B0%E8%80%85%E4%BC%9A%E8%AF%B4%E4%BA%86%E4%BB%80%E4%B9%88",
          "source": "bilibili 热搜",
          "ranks": [
            10,
            22
          ],
          "is_new": false,
          "appearance_count": 2,
          "time_info": "[12时15分 ~ 17时17分]"
        },
        {
          "title": "美以历史上十分罕见！“特朗普可能意识到自己被骗了”",
          "url": "https://news.ifeng.com/c/8u33RqAGLKg",
          "source": "凤凰网",
          "ranks": [
            10
          ],
          "is_new": false,
          "appearance_count": 2,
          "time_info": "[20时56分 ~ 20时57分]"
        },
        {
          "title": "特朗普G7峰会迟到后宣告我是老大",
          "url": "https://s.weibo.com/weibo?q=%23%E7%89%B9%E6%9C%97%E6%99%AEG7%E5%B3%B0%E4%BC%9A%E8%BF%9F%E5%88%B0%E5%90%8E%E5%AE%A3%E5%91%8A%E6%88%91%E6%98%AF%E8%80%81%E5%A4%A7%23&t=31&band_rank=25&Refer=top",
          "source": "微博",
          "ranks": [
            25
          ],
          "is_new": false,
          "appearance_count": 2,
          "time_info": "[05时10分 ~ 05时11分]"
        },
        {
          "title": "首秀！美联储主席沃什：坚守2%通胀目标，成立五个特别工作组，个人未提交点阵图",
          "url": "https://wallstreetcn.com/articles/3774941",
          "source": "华尔街见闻",
          "ranks": [
            6
          ],
          "is_new": false,
          "appearance_count": 1,
          "time_info": "07时28分"
        },
        {
          "title": "沃什首秀露“鹰爪”！市场预期彻底逆转：美联储10月前加息已被充分定价",
          "url": "https://www.cls.cn/detail/2403192",
          "source": "财联社热门",
          "ranks": [
            6
          ],
          "is_new": false,
          "appearance_count": 1,
          "time_info": "17时17分"
        },
        {
          "title": "美以历史上十分罕见！“特朗普可能意识到自己被骗了…”",
          "url": "https://news.ifeng.com/c/8u33RqAGLKg",
          "source": "凤凰网",
          "ranks": [
            6
          ],
          "is_new": false,
          "appearance_count": 1,
          "time_info": "17时17分"
        },
        {
          "title": "美联储FOMC将于十分钟后公布利率决议和经济预期摘要。",
          "url": "https://flash.jin10.com/detail/20260618015000001800",
          "source": "金十数据",
          "ranks": [
            6
          ],
          "is_new": false,
          "appearance_count": 1,
          "time_info": "02时23分"
        },
        {
          "title": "DeepTalk：沃什在玩一场危险的“信息真空”，这届美联储要失控？",
          "url": "https://flash.jin10.com/detail/20260618204041284800",
          "source": "金十数据",
          "ranks": [
            6
          ],
          "is_new": true,
          "appearance_count": 1,
          "time_info": "20时57分"
        },
        {
          "title": "美联储6月决议声明和新闻发布会关注点",
          "url": "https://wallstreetcn.com/livenews/3121069",
          "source": "华尔街见闻-快讯",
          "ranks": [
            6
          ],
          "is_new": false,
          "appearance_count": 1,
          "time_info": "02时23分"
        },
        {
          "title": "特朗普称霍尔木兹海峡周五全面重开、或近期恢复俄油制裁，伊朗称协议要求以从黎撤军",
          "url": "https://wallstreetcn.com/articles/3774815",
          "source": "华尔街见闻",
          "ranks": [
            7
          ],
          "is_new": false,
          "appearance_count": 1,
          "time_info": "02时23分"
        },
        {
          "title": "巴西总统卢拉：我预计美国总统特朗普不会干预巴西选举。",
          "url": "https://flash.jin10.com/detail/20260618014915001800",
          "source": "金十数据",
          "ranks": [
            7
          ],
          "is_new": false,
          "appearance_count": 1,
          "time_info": "02时23分"
        },
        {
          "title": "特朗普：我喜欢“伊朗协议不奏效就怪罪万斯”这个想法",
          "url": "https://wallstreetcn.com/livenews/3121174",
          "source": "华尔街见闻-快讯",
          "ranks": [
            7
          ],
          "is_new": false,
          "appearance_count": 1,
          "time_info": "02时23分"
        },
        {
          "title": "特朗普G7答UP主提问点赞中国",
          "url": "https://search.bilibili.com/all?keyword=%E7%89%B9%E6%9C%97%E6%99%AEG7%E7%AD%94UP%E4%B8%BB%E6%8F%90%E9%97%AE%E7%82%B9%E8%B5%9E%E4%B8%AD%E5%9B%BD",
          "source": "bilibili 热搜",
          "ranks": [
            9
          ],
          "is_new": false,
          "appearance_count": 1,
          "time_info": "17时17分"
        },
        {
          "title": "巴西总统卢拉：美国总统特朗普说得太多，倾听得太少。",
          "url": "https://flash.jin10.com/detail/20260618014754366800",
          "source": "金十数据",
          "ranks": [
            9
          ],
          "is_new": false,
          "appearance_count": 1,
          "time_info": "02时23分"
        },
        {
          "title": "美国总统特朗普：签署了伊朗谅解备忘录。",
          "url": "https://flash.jin10.com/detail/20260618070556543800",
          "source": "金十数据",
          "ranks": [
            9
          ],
          "is_new": false,
          "appearance_count": 1,
          "time_info": "07时28分"
        },
        {
          "title": "FED独立性保住了？特朗普“笃信”沃什：按兵不动没问题，可能会加息！",
          "url": "https://www.cls.cn/detail/2403030",
          "source": "财联社热门",
          "ranks": [
            11
          ],
          "is_new": false,
          "appearance_count": 1,
          "time_info": "12时15分"
        },
        {
          "title": "摩根大通全球固收负责人米歇尔：如果美联储放弃宽松偏向，将不会有异议。",
          "url": "https://flash.jin10.com/detail/20260618014528921800",
          "source": "金十数据",
          "ranks": [
            11
          ],
          "is_new": false,
          "appearance_count": 1,
          "time_info": "02时23分"
        },
        {
          "title": "提醒：美国总统特朗普在七国集团（G7）峰会期间的新闻发布会结束。",
          "url": "https://wallstreetcn.com/livenews/3121170",
          "source": "华尔街见闻-快讯",
          "ranks": [
            11
          ],
          "is_new": false,
          "appearance_count": 1,
          "time_info": "02时23分"
        },
        {
          "title": "沃什美联储“首秀”前瞻：关注这N大看点！",
          "url": "https://flash.jin10.com/detail/20260618014449906800",
          "source": "金十数据",
          "ranks": [
            12
          ],
          "is_new": false,
          "appearance_count": 1,
          "time_info": "02时23分"
        },
        {
          "title": "巴西总统卢拉：谈判结束后，我不介意与美国总统特朗普安排新会议。",
          "url": "https://flash.jin10.com/detail/20260618014416355800",
          "source": "金十数据",
          "ranks": [
            13
          ],
          "is_new": false,
          "appearance_count": 1,
          "time_info": "02时23分"
        },
        {
          "title": "高盛：美联储最早可能9月加息，不排除还有第二次、第三次",
          "url": "https://flash.jin10.com/detail/20260618112426212800",
          "source": "金十数据",
          "ranks": [
            13
          ],
          "is_new": false,
          "appearance_count": 1,
          "time_info": "12时15分"
        },
        {
          "title": "标普500指数收跌91.25点，跌幅1.21%，报7420.10点。 道琼斯工业平均指数收跌507.12点，跌幅0.98%，报51492.55点。 纳斯达克综合指数（纳指）收跌354.688点，跌幅1.35%，报26021.656点。 纳斯达克100指数收跌297.181点，跌幅0.99%，报29670.948点。 纳斯达克科技市值加权指数收跌0.57%，报2911.3000点，美联储披露经济预期概要（SEP）之前高位持稳，美联储主席沃什新闻发布会开始后刷新日高。 费城半导体指数收涨182.848点，涨幅1.38%，报13477.072点。 费城证交所KBW银行指数收跌0.37%，报180.93点。 道琼斯KBW地区银行指数收跌1.80%，报137.43点。 罗素2000指数收跌0.72%，报2917.982点。 纳斯达克生物科技指数收涨1.10%，报6018.75点，逼近4月17日所创收盘历史最高位6131.78点和盘中历史最高位6142.03点。 标普中盘股400指数收跌1.24%，纳斯达克美国中等市值指数跌1.46%。 恐慌指数VIX收涨12.31%，报18.43。",
          "url": "https://wallstreetcn.com/livenews/3121245",
          "source": "华尔街见闻-快讯",
          "ranks": [
            13
          ],
          "is_new": false,
          "appearance_count": 1,
          "time_info": "05时11分"
        },
        {
          "title": "智谱等中国大模型何时赶上Fable水平？马斯克：或在2027年一季度",
          "url": "https://wallstreetcn.com/livenews/3121694",
          "source": "华尔街见闻-快讯",
          "ranks": [
            13
          ],
          "is_new": true,
          "appearance_count": 1,
          "time_info": "20时57分"
        },
        {
          "title": "巴西总统卢拉：我现在没有理由与美国总统特朗普交谈，我们正处于谈判中。",
          "url": "https://flash.jin10.com/detail/20260618014411364800",
          "source": "金十数据",
          "ranks": [
            14
          ],
          "is_new": false,
          "appearance_count": 1,
          "time_info": "02时23分"
        },
        {
          "title": "分析师：美联储加息条件尚未成熟，但理由正在累积",
          "url": "https://flash.jin10.com/detail/20260618112329861800",
          "source": "金十数据",
          "ranks": [
            14
          ],
          "is_new": false,
          "appearance_count": 1,
          "time_info": "12时15分"
        },
        {
          "title": "拒绝前瞻指引、回避利率路径 沃什重塑美联储沟通模式",
          "url": "https://flash.jin10.com/detail/20260618035753049800",
          "source": "金十数据",
          "ranks": [
            15
          ],
          "is_new": false,
          "appearance_count": 1,
          "time_info": "05时11分"
        },
        {
          "title": "交易员全面定价美联储到2027年一季度将加息两次。",
          "url": "https://wallstreetcn.com/livenews/3121242",
          "source": "华尔街见闻-快讯",
          "ranks": [
            15
          ],
          "is_new": false,
          "appearance_count": 1,
          "time_info": "05时11分"
        },
        {
          "title": "美联储暗示可能加息，拉美资产普遍下滑",
          "url": "https://wallstreetcn.com/livenews/3121286",
          "source": "华尔街见闻-快讯",
          "ranks": [
            15
          ],
          "is_new": false,
          "appearance_count": 1,
          "time_info": "07时28分"
        },
        {
          "title": "摩根大通全球固收负责人米歇尔：美联储主席沃什注定会让特朗普失望。",
          "url": "https://flash.jin10.com/detail/20260618014345044800",
          "source": "金十数据",
          "ranks": [
            16
          ],
          "is_new": false,
          "appearance_count": 1,
          "time_info": "02时23分"
        },
        {
          "title": "市场已完全定价，到2027年第一季度末美联储将加息两次。",
          "url": "https://flash.jin10.com/detail/20260618035445341800",
          "source": "金十数据",
          "ranks": [
            16
          ],
          "is_new": false,
          "appearance_count": 1,
          "time_info": "05时11分"
        },
        {
          "title": "美联储按兵不动，非美货币在沃什首秀日普跌",
          "url": "https://wallstreetcn.com/livenews/3121241",
          "source": "华尔街见闻-快讯",
          "ranks": [
            16
          ],
          "is_new": false,
          "appearance_count": 1,
          "time_info": "05时11分"
        },
        {
          "title": "摩根大通全球固收负责人米歇尔：对美联储主席沃什而言，问题在于制度改革意味着什么。",
          "url": "https://flash.jin10.com/detail/20260618014344572800",
          "source": "金十数据",
          "ranks": [
            17
          ],
          "is_new": false,
          "appearance_count": 1,
          "time_info": "02时23分"
        },
        {
          "title": "美联储决议后市场押注骤变 市场积极定价年底前加息两次的预期",
          "url": "https://flash.jin10.com/detail/20260618035237224800",
          "source": "金十数据",
          "ranks": [
            17
          ],
          "is_new": false,
          "appearance_count": 1,
          "time_info": "05时11分"
        },
        {
          "title": "美国总统特朗普：正在调查“美国袭击伊朗学校”一事。",
          "url": "https://wallstreetcn.com/livenews/3121161",
          "source": "华尔街见闻-快讯",
          "ranks": [
            17
          ],
          "is_new": false,
          "appearance_count": 1,
          "time_info": "02时23分"
        },
        {
          "title": "沃什首秀：点阵图偏鹰，但美联储不再急于“指路” | 一文看懂6月发布会",
          "url": "https://flash.jin10.com/detail/20260618034535647800",
          "source": "金十数据",
          "ranks": [
            18
          ],
          "is_new": false,
          "appearance_count": 1,
          "time_info": "05时11分"
        },
        {
          "title": "沃什上任后首次议息会议，美联储如期「按兵不动」，议息声明大修改，怎样解读？",
          "url": "https://www.zhihu.com/question/2050851932814537240",
          "source": "知乎",
          "ranks": [
            18
          ],
          "is_new": false,
          "appearance_count": 1,
          "time_info": "12时15分"
        },
        {
          "title": "据华尔街日报：美联储主席沃什首次新闻发布会时间略短于往常。",
          "url": "https://flash.jin10.com/detail/20260618034528388800",
          "source": "金十数据",
          "ranks": [
            19
          ],
          "is_new": false,
          "appearance_count": 1,
          "time_info": "05时11分"
        },
        {
          "title": "特朗普：日本首相是我的头号粉丝",
          "url": "https://www.baidu.com/s?wd=%E7%89%B9%E6%9C%97%E6%99%AE%EF%BC%9A%E6%97%A5%E6%9C%AC%E9%A6%96%E7%9B%B8%E6%98%AF%E6%88%91%E7%9A%84%E5%A4%B4%E5%8F%B7%E7%B2%89%E4%B8%9D",
          "source": "百度热搜",
          "ranks": [
            20
          ],
          "is_new": false,
          "appearance_count": 1,
          "time_info": "12时15分"
        },
        {
          "title": "金十数据整理：美联储FOMC声明及沃什发布会重点一览",
          "url": "https://flash.jin10.com/detail/20260618034347861800",
          "source": "金十数据",
          "ranks": [
            20
          ],
          "is_new": false,
          "appearance_count": 1,
          "time_info": "05时11分"
        },
        {
          "title": "巴西总统卢拉：我并没有要求在G7峰会上与美国总统特朗普进行双边会晤。",
          "url": "https://flash.jin10.com/detail/20260618014034015800",
          "source": "金十数据",
          "ranks": [
            21
          ],
          "is_new": false,
          "appearance_count": 1,
          "time_info": "02时23分"
        },
        {
          "title": "特朗普：美伊谅解备忘录可能在18日或19日签署",
          "url": "https://wallstreetcn.com/livenews/3121156",
          "source": "华尔街见闻-快讯",
          "ranks": [
            21
          ],
          "is_new": false,
          "appearance_count": 1,
          "time_info": "02时23分"
        },
        {
          "title": "美国总统特朗普：上周日与俄罗斯总统普京通话。",
          "url": "https://wallstreetcn.com/livenews/3121152",
          "source": "华尔街见闻-快讯",
          "ranks": [
            24
          ],
          "is_new": false,
          "appearance_count": 1,
          "time_info": "02时23分"
        },
        {
          "title": "美官员称特朗普亲自提前签署美伊谅解备忘录",
          "url": "https://wallstreetcn.com/livenews/3121274",
          "source": "华尔街见闻-快讯",
          "ranks": [
            24
          ],
          "is_new": false,
          "appearance_count": 1,
          "time_info": "07时28分"
        },
        {
          "title": "新兴市场股票指数抹去涨幅，因美联储转鹰。",
          "url": "https://flash.jin10.com/detail/20260618033243142800",
          "source": "金十数据",
          "ranks": [
            25
          ],
          "is_new": false,
          "appearance_count": 1,
          "time_info": "05时11分"
        },
        {
          "title": "美国总统特朗普：希望获得扩大版“亚伯拉罕协议”。",
          "url": "https://wallstreetcn.com/livenews/3121151",
          "source": "华尔街见闻-快讯",
          "ranks": [
            25
          ],
          "is_new": false,
          "appearance_count": 1,
          "time_info": "02时23分"
        },
        {
          "title": "以色列始终认为不受美伊协议约束 特朗普直言以战术不可接受",
          "url": "https://flash.jin10.com/detail/20260618111057786800",
          "source": "金十数据",
          "ranks": [
            26
          ],
          "is_new": false,
          "appearance_count": 1,
          "time_info": "12时15分"
        },
        {
          "title": "美国总统特朗普：将不得不为黎巴嫩付出努力。",
          "url": "https://wallstreetcn.com/livenews/3121150",
          "source": "华尔街见闻-快讯",
          "ranks": [
            26
          ],
          "is_new": false,
          "appearance_count": 1,
          "time_info": "02时23分"
        },
        {
          "title": "美国总统特朗普：我在想，我们或许无法围绕美国墨西哥加拿大贸易协议（USMCA）达成共识。",
          "url": "https://wallstreetcn.com/livenews/3121230",
          "source": "华尔街见闻-快讯",
          "ranks": [
            26
          ],
          "is_new": false,
          "appearance_count": 1,
          "time_info": "05时11分"
        },
        {
          "title": "邵永灵：泽连斯基和欧洲向特朗普低头",
          "url": "https://www.toutiao.com/trending/7652352370063445558/",
          "source": "今日头条",
          "ranks": [
            27
          ],
          "is_new": false,
          "appearance_count": 1,
          "time_info": "02时23分"
        },
        {
          "title": "美国总统特朗普：试图让哈马斯解除武装。",
          "url": "https://wallstreetcn.com/livenews/3121149",
          "source": "华尔街见闻-快讯",
          "ranks": [
            27
          ],
          "is_new": false,
          "appearance_count": 1,
          "time_info": "02时23分"
        },
        {
          "title": "交易员在美联储释放鹰派信号后，完全定价10月前加息",
          "url": "https://wallstreetcn.com/livenews/3121229",
          "source": "华尔街见闻-快讯",
          "ranks": [
            27
          ],
          "is_new": false,
          "appearance_count": 1,
          "time_info": "05时11分"
        },
        {
          "title": "美联储6月利率决议和主席沃什首次新闻发布会要点总结",
          "url": "https://wallstreetcn.com/livenews/3121227",
          "source": "华尔街见闻-快讯",
          "ranks": [
            29
          ],
          "is_new": false,
          "appearance_count": 1,
          "time_info": "05时11分"
        },
        {
          "title": "美国总统特朗普：关于移除伊朗浓缩铀库存的谈判将立即启动。",
          "url": "https://wallstreetcn.com/livenews/3121146",
          "source": "华尔街见闻-快讯",
          "ranks": [
            30
          ],
          "is_new": false,
          "appearance_count": 1,
          "time_info": "02时23分"
        },
        {
          "title": "提醒：美联储主席凯文·沃什的新闻发布会结束。",
          "url": "https://wallstreetcn.com/livenews/3121226",
          "source": "华尔街见闻-快讯",
          "ranks": [
            30
          ],
          "is_new": false,
          "appearance_count": 1,
          "time_info": "05时11分"
        }
      ]
    },
    {
      "keyword_group": "美股 A股 港股 美债 美元 石油 战争",
      "match_count": 61,
      "titles": [
        {
          "title": "市场静待沃什\"首秀\"，美股指涨跌互现，道指再新高，科技股承压，美油跌近6%",
          "url": "https://wallstreetcn.com/articles/3774774",
          "source": "华尔街见闻",
          "ranks": [
            3,
            4
          ],
          "is_new": false,
          "appearance_count": 4,
          "time_info": "[02时23分 ~ 07时28分]"
        },
        {
          "title": "市场静待沃什首秀，美股指走高，半导体股多数上涨，SpaceX跌幅扩大至4%，油价涨1%",
          "url": "https://wallstreetcn.com/articles/3774887",
          "source": "华尔街见闻",
          "ranks": [
            5,
            4
          ],
          "is_new": false,
          "appearance_count": 3,
          "time_info": "[02时23分 ~ 05时11分]"
        },
        {
          "title": "美股收盘：沃什首秀吓坏市场！三大指数尾盘跳水",
          "url": "https://www.cls.cn/detail/2403003",
          "source": "财联社热门",
          "ranks": [
            3,
            4
          ],
          "is_new": false,
          "appearance_count": 2,
          "time_info": "[07时28分 ~ 12时15分]"
        },
        {
          "title": "A股午评：创业板指半日收涨1.39% 再创近11年来新高",
          "url": "https://flash.jin10.com/detail/20260618114054631800",
          "source": "金十数据",
          "ranks": [
            2
          ],
          "is_new": false,
          "appearance_count": 1,
          "time_info": "12时15分"
        },
        {
          "title": "美元指数17日上涨",
          "url": "https://flash.jin10.com/detail/20260618043622317800",
          "source": "金十数据",
          "ranks": [
            3
          ],
          "is_new": false,
          "appearance_count": 1,
          "time_info": "05时11分"
        },
        {
          "title": "必胜客被卖了，百胜中国 12 亿美元收购中国大陆品牌所有权，卖身原因有哪些？如何看待其中国市场前景？",
          "url": "https://www.zhihu.com/question/2050336798279034583",
          "source": "知乎",
          "ranks": [
            3,
            15,
            10
          ],
          "is_new": false,
          "appearance_count": 4,
          "time_info": "[02时23分 ~ 07时28分]"
        },
        {
          "title": "博主：A股正在发生三大结构性逆转",
          "url": "https://www.toutiao.com/trending/7652346288553332230/",
          "source": "今日头条",
          "ranks": [
            4
          ],
          "is_new": false,
          "appearance_count": 1,
          "time_info": "02时23分"
        },
        {
          "title": "伊朗议会议长卡利巴夫：根据谅解备忘录，已分配3000亿美元用于投资伊朗，其中一部分将用于重建。",
          "url": "https://flash.jin10.com/detail/20260618042530620800",
          "source": "金十数据",
          "ranks": [
            4
          ],
          "is_new": false,
          "appearance_count": 1,
          "time_info": "05时11分"
        },
        {
          "title": "周三（6月17日），美股存储芯片与硬件供应链指数涨1.78%，报250.51点，过半交易时间持稳于256点附近，北京时间02:00美联储披露经济预期概要（SEP）之后显著回吐涨幅，美联储主席沃什新闻发布会开始后一度冲高至260点上方刷新日高。 成分股西部数据涨超4.5%，应用材料涨超4.3%，希捷科技、美光科技、拉姆研究至少涨超1%，闪迪、Rambus则跌超1%。",
          "url": "https://wallstreetcn.com/livenews/3121255",
          "source": "华尔街见闻-快讯",
          "ranks": [
            4
          ],
          "is_new": false,
          "appearance_count": 1,
          "time_info": "05时11分"
        },
        {
          "title": "美股七巨头收盘播报｜周三（6月17日），美国科技股七巨头（Magnificent 7）指数跌2.38%，报210.21点，跳空低开之后持续下挫，北京时间02:00美联储宣布按兵不动、披露经济预期概要（SEP）后显著地加速下跌，美联储主席凯文·沃什新闻发布会开始后再度加速下跌。 “超大”市值科技股指数跌1.56%，报432.59点，美联储决议声明发布后显著下挫，沃什新闻发布会开始之后冲高回落。",
          "url": "https://wallstreetcn.com/livenews/3121254",
          "source": "华尔街见闻-快讯",
          "ranks": [
            5
          ],
          "is_new": false,
          "appearance_count": 1,
          "time_info": "05时11分"
        },
        {
          "title": "美伊协议核心条款曝光：伊朗石油出口即刻解禁，核项目维持现状，海峡快速重启仍存变数",
          "url": "https://wallstreetcn.com/articles/3774848",
          "source": "华尔街见闻",
          "ranks": [
            8
          ],
          "is_new": false,
          "appearance_count": 4,
          "time_info": "[02时23分 ~ 07时28分]"
        },
        {
          "title": "6月18日投资避雷针：昨日晚间逾70家A股公司提示风险",
          "url": "https://www.cls.cn/detail/2403062",
          "source": "财联社热门",
          "ranks": [
            9,
            4
          ],
          "is_new": false,
          "appearance_count": 2,
          "time_info": "[12时15分 ~ 17时17分]"
        },
        {
          "title": "港股博弈现冰火两重天 建滔集团、长飞光纤光缆遭空头加码",
          "url": "https://www.cls.cn/detail/2403381",
          "source": "财联社热门",
          "ranks": [
            9
          ],
          "is_new": false,
          "appearance_count": 2,
          "time_info": "[20时56分 ~ 20时57分]"
        },
        {
          "title": "特朗普：4周耗尽石油储备！美国最大商业原油储存枢纽库存跌至警戒线",
          "url": "https://wallstreetcn.com/articles/3774931",
          "source": "华尔街见闻",
          "ranks": [
            10
          ],
          "is_new": false,
          "appearance_count": 2,
          "time_info": "[20时56分 ~ 20时57分]"
        },
        {
          "title": "联想集团(00992.HK)：拟发行于2033年到期的20亿美元美元零息可换股债券；拟同步购回于2029年到期的6.75亿美元2.50%可换股债券；拟根据股份回购授权于市场上进行股份回购。",
          "url": "https://flash.jin10.com/detail/20260618071453653800",
          "source": "金十数据",
          "ranks": [
            6
          ],
          "is_new": false,
          "appearance_count": 1,
          "time_info": "07时28分"
        },
        {
          "title": "美元指数上涨0.2%，至100.6，为3月底以来最高水平。",
          "url": "https://flash.jin10.com/detail/20260618171121271800",
          "source": "金十数据",
          "ranks": [
            7
          ],
          "is_new": false,
          "appearance_count": 1,
          "time_info": "17时17分"
        },
        {
          "title": "华为公布Wi-Fi 7专利许可费率 每台设备0.5美元",
          "url": "https://wallstreetcn.com/livenews/3121703",
          "source": "华尔街见闻-快讯",
          "ranks": [
            7
          ],
          "is_new": true,
          "appearance_count": 1,
          "time_info": "20时57分"
        },
        {
          "title": "周三（6月17日），韩元兑美元最终跌0.45%，报1515韩元。",
          "url": "https://wallstreetcn.com/livenews/3121173",
          "source": "华尔街见闻-快讯",
          "ranks": [
            8
          ],
          "is_new": false,
          "appearance_count": 1,
          "time_info": "02时23分"
        },
        {
          "title": "周三（6月17日），美股降息赢家指数跌2.29%，报93.60点，彭博数据显示，北京时间21:51（美股盘初）曾瞬间跳水至零，02:00美联储决议声明发布后转跌。",
          "url": "https://wallstreetcn.com/livenews/3121251",
          "source": "华尔街见闻-快讯",
          "ranks": [
            8
          ],
          "is_new": false,
          "appearance_count": 1,
          "time_info": "05时11分"
        },
        {
          "title": "纽元兑美元走高，新西兰一季度GDP同比增幅超预期。",
          "url": "https://wallstreetcn.com/livenews/3121293",
          "source": "华尔街见闻-快讯",
          "ranks": [
            8
          ],
          "is_new": false,
          "appearance_count": 1,
          "time_info": "07时28分"
        },
        {
          "title": "周三（6月17日），美联储隔夜逆回购协议（RRP）使用规模为68.28亿美元（交易对手16家），上个交易日报107.21亿美元。",
          "url": "https://wallstreetcn.com/livenews/3121172",
          "source": "华尔街见闻-快讯",
          "ranks": [
            9
          ],
          "is_new": false,
          "appearance_count": 1,
          "time_info": "02时23分"
        },
        {
          "title": "周三（6月17日），美股行业ETF普遍收跌，网络股指数ETF跌2.89%，可选消费ETF、日常消费品等至多跌2.51%，区域银行ETF、银行业ETF、能源业ETF、全球航空业ETF至多跌1.90%，半导体指数ETF则涨1.29%。",
          "url": "https://wallstreetcn.com/livenews/3121250",
          "source": "华尔街见闻-快讯",
          "ranks": [
            9
          ],
          "is_new": false,
          "appearance_count": 1,
          "time_info": "05时11分"
        },
        {
          "title": "金十图示：2026年06月17日（周三）美股热门股票行情一览（美股收盘）",
          "url": "https://flash.jin10.com/detail/20260618040640588800",
          "source": "金十数据",
          "ranks": [
            10
          ],
          "is_new": false,
          "appearance_count": 1,
          "time_info": "05时11分"
        },
        {
          "title": "Momenta港股IPO获中国证监会备案",
          "url": "https://flash.jin10.com/detail/20260618170915374800",
          "source": "金十数据",
          "ranks": [
            10
          ],
          "is_new": false,
          "appearance_count": 1,
          "time_info": "17时17分"
        },
        {
          "title": "金十图示：2026年06月17日（周三）热门中概股行情一览（美股收盘）",
          "url": "https://flash.jin10.com/detail/20260618040638076800",
          "source": "金十数据",
          "ranks": [
            11
          ],
          "is_new": false,
          "appearance_count": 1,
          "time_info": "05时11分"
        },
        {
          "title": "综合一份文件与三名石油官员的信息得知，伊拉克南部多个油田的石油产量增长大约50万桶/日，至日产150万桶/日。 目前，抵达（伊拉克）多个石油出口枢纽的油轮增加。（路透）",
          "url": "https://wallstreetcn.com/livenews/3121290",
          "source": "华尔街见闻-快讯",
          "ranks": [
            11
          ],
          "is_new": false,
          "appearance_count": 1,
          "time_info": "07时28分"
        },
        {
          "title": "德银：上调美光目标价至1500美元 预计存储短缺将持续至2028年",
          "url": "https://www.cls.cn/detail/2402856",
          "source": "财联社热门",
          "ranks": [
            12
          ],
          "is_new": false,
          "appearance_count": 1,
          "time_info": "12时15分"
        },
        {
          "title": "路透调查：尽管日本政府保证供应充足，但几乎所有日本公司都对石油及石油产品的采购表示担忧。",
          "url": "https://flash.jin10.com/detail/20260618070104198800",
          "source": "金十数据",
          "ranks": [
            12
          ],
          "is_new": false,
          "appearance_count": 1,
          "time_info": "07时28分"
        },
        {
          "title": "美股收盘：沃什美联储首秀 三大股指集体收跌",
          "url": "https://flash.jin10.com/detail/20260618040054736800",
          "source": "金十数据",
          "ranks": [
            13
          ],
          "is_new": false,
          "appearance_count": 1,
          "time_info": "05时11分"
        },
        {
          "title": "在岸人民币兑美元北京时间16:30官方收报6.7623，较上一交易日官方收盘价跌54点，较上日夜盘收盘涨7点。",
          "url": "https://wallstreetcn.com/livenews/3121562",
          "source": "华尔街见闻-快讯",
          "ranks": [
            14
          ],
          "is_new": false,
          "appearance_count": 1,
          "time_info": "17时17分"
        },
        {
          "title": "美伊协议或让伊朗石油收入“一夜回春”：年入或超600亿美元，全球油价面临新变数",
          "url": "https://flash.jin10.com/detail/20260618112249385800",
          "source": "金十数据",
          "ranks": [
            15
          ],
          "is_new": false,
          "appearance_count": 1,
          "time_info": "12时15分"
        },
        {
          "title": "大摩：市场已“跨过”伊朗战争的影响",
          "url": "https://wallstreetcn.com/livenews/3121163",
          "source": "华尔街见闻-快讯",
          "ranks": [
            15
          ],
          "is_new": false,
          "appearance_count": 1,
          "time_info": "02时23分"
        },
        {
          "title": "英镑兑美元由涨转跌，下跌0.1%至日内低点1.3278。",
          "url": "https://wallstreetcn.com/livenews/3121561",
          "source": "华尔街见闻-快讯",
          "ranks": [
            15
          ],
          "is_new": false,
          "appearance_count": 1,
          "time_info": "17时17分"
        },
        {
          "title": "最近24小时，MarketVectorTM数字资产100小盘指数涨1.35%，暂报2413.24点，北京时间10:29刷新期内高位至2458.69点，随后持续下挫，20:30刷新日低至2350.11点。 MarketVectorTM数字资产100中盘指数涨1.65%，报2781.37点，00:29曾达到2809.63点。 MarketVector数字资产100指数涨0.16%，报13086.58点。 目前，Solana跌0.17%，狗狗币跌0.37%，XRP跌0.72%。 比特币涨0.35%，暂报65824.80美元；以太坊跌1.42%，暂报1769.49美元。",
          "url": "https://wallstreetcn.com/livenews/3121162",
          "source": "华尔街见闻-快讯",
          "ranks": [
            16
          ],
          "is_new": false,
          "appearance_count": 1,
          "time_info": "02时23分"
        },
        {
          "title": "iPhone18Pro或涨价270美元",
          "url": "https://www.baidu.com/s?wd=iPhone18Pro%E6%88%96%E6%B6%A8%E4%BB%B7270%E7%BE%8E%E5%85%83",
          "source": "百度热搜",
          "ranks": [
            17
          ],
          "is_new": false,
          "appearance_count": 1,
          "time_info": "12时15分"
        },
        {
          "title": "立讯精密港股上市获中国证监会备案",
          "url": "https://flash.jin10.com/detail/20260618170400921800",
          "source": "金十数据",
          "ranks": [
            17
          ],
          "is_new": false,
          "appearance_count": 1,
          "time_info": "17时17分"
        },
        {
          "title": "美股盘前，半导体股普涨，英特尔涨近9%",
          "url": "https://wallstreetcn.com/livenews/3121558",
          "source": "华尔街见闻-快讯",
          "ranks": [
            17
          ],
          "is_new": false,
          "appearance_count": 1,
          "time_info": "17时17分"
        },
        {
          "title": "全球资本正在回流美国 A股会失血吗",
          "url": "https://www.toutiao.com/trending/7652596192932531722/",
          "source": "今日头条",
          "ranks": [
            18
          ],
          "is_new": false,
          "appearance_count": 1,
          "time_info": "17时17分"
        },
        {
          "title": "据塔斯社：当地市长表示，有无人机袭击了莫斯科石油精炼厂。",
          "url": "https://flash.jin10.com/detail/20260618112134056800",
          "source": "金十数据",
          "ranks": [
            18
          ],
          "is_new": false,
          "appearance_count": 1,
          "time_info": "12时15分"
        },
        {
          "title": "美元指数日内涨幅达1.0%，报100.5602。",
          "url": "https://wallstreetcn.com/livenews/3121239",
          "source": "华尔街见闻-快讯",
          "ranks": [
            18
          ],
          "is_new": false,
          "appearance_count": 1,
          "time_info": "05时11分"
        },
        {
          "title": "多家A股公司提示风险",
          "url": "https://www.toutiao.com/trending/7652205334456025130/",
          "source": "今日头条",
          "ranks": [
            19
          ],
          "is_new": false,
          "appearance_count": 1,
          "time_info": "02时23分"
        },
        {
          "title": "美伊签了！美股期货直线拉升",
          "url": "https://www.baidu.com/s?wd=%E7%BE%8E%E4%BC%8A%E7%AD%BE%E4%BA%86%EF%BC%81%E7%BE%8E%E8%82%A1%E6%9C%9F%E8%B4%A7%E7%9B%B4%E7%BA%BF%E6%8B%89%E5%8D%87",
          "source": "百度热搜",
          "ranks": [
            19
          ],
          "is_new": false,
          "appearance_count": 1,
          "time_info": "12时15分"
        },
        {
          "title": "A股消费板块局部异动，大连友谊三连板，天虹股份、中百集团、金种子酒、一致魔芋、朱老六等跟涨。",
          "url": "https://flash.jin10.com/detail/20260618112008511800",
          "source": "金十数据",
          "ranks": [
            20
          ],
          "is_new": false,
          "appearance_count": 1,
          "time_info": "12时15分"
        },
        {
          "title": "特朗普：如果不将资金退还给伊朗，那将对美元不利",
          "url": "https://wallstreetcn.com/livenews/3121158",
          "source": "华尔街见闻-快讯",
          "ranks": [
            20
          ],
          "is_new": false,
          "appearance_count": 1,
          "time_info": "02时23分"
        },
        {
          "title": "伊朗外交部发言人：伊朗必须能够顺利出售其石油，运输和保险均无障碍，并且必须获得石油出售所得收入。",
          "url": "https://flash.jin10.com/detail/20260618063726757800",
          "source": "金十数据",
          "ranks": [
            21
          ],
          "is_new": false,
          "appearance_count": 1,
          "time_info": "07时28分"
        },
        {
          "title": "野村：美联储政策料将主导美元兑日元走势",
          "url": "https://flash.jin10.com/detail/20260618111856997800",
          "source": "金十数据",
          "ranks": [
            21
          ],
          "is_new": false,
          "appearance_count": 1,
          "time_info": "12时15分"
        },
        {
          "title": "伊朗所发文本显示美国将在签署谅解备忘录后立即发放伊朗石油豁免",
          "url": "https://wallstreetcn.com/livenews/3121680",
          "source": "华尔街见闻-快讯",
          "ranks": [
            21
          ],
          "is_new": true,
          "appearance_count": 1,
          "time_info": "20时57分"
        },
        {
          "title": "WTI原油期货低开1.7%，交投于75美元附近，投资者关注伊朗协议生效。",
          "url": "https://wallstreetcn.com/livenews/3121276",
          "source": "华尔街见闻-快讯",
          "ranks": [
            22
          ],
          "is_new": false,
          "appearance_count": 1,
          "time_info": "07时28分"
        },
        {
          "title": "英特尔美股盘前涨近7%，特朗普称将帮助英特尔，因为我们需要设计和制造芯片。",
          "url": "https://wallstreetcn.com/livenews/3121546",
          "source": "华尔街见闻-快讯",
          "ranks": [
            22
          ],
          "is_new": false,
          "appearance_count": 1,
          "time_info": "17时17分"
        },
        {
          "title": "港股恒生指数跌超2%，恒生科技指数跌1.64%，中国人寿(02628.HK)跌超7%，中国宏桥(01378.HK)跌超6%，信义玻璃(00868.HK)、龙湖集团(00960.HK)均跌5%，紫金矿业(02899.HK)、中国海外发展(00688.HK)、泡泡玛特(09992.HK)均跌超4.5%。",
          "url": "https://flash.jin10.com/detail/20260618111700330800",
          "source": "金十数据",
          "ranks": [
            23
          ],
          "is_new": false,
          "appearance_count": 1,
          "time_info": "12时15分"
        },
        {
          "title": "伊朗：（美西方）今天必须就开始撤销石油制裁。 伊朗应该毫无阻力地出售石油。 必须能够在我们选择的任何时候动用被冻结的资产。 必须能够用资金进行任何采购。 美国60天内不得增兵或加码制裁。 美国有责任强迫以色列遵守协议。",
          "url": "https://wallstreetcn.com/livenews/3121275",
          "source": "华尔街见闻-快讯",
          "ranks": [
            23
          ],
          "is_new": false,
          "appearance_count": 1,
          "time_info": "07时28分"
        },
        {
          "title": "美元兑日元USD/JPY升至2024年7月以来的最高水平，现报160.75。",
          "url": "https://flash.jin10.com/detail/20260618033319525800",
          "source": "金十数据",
          "ranks": [
            24
          ],
          "is_new": false,
          "appearance_count": 1,
          "time_info": "05时11分"
        },
        {
          "title": "美股费城银行指数转跌，此前一度涨1.6%。",
          "url": "https://wallstreetcn.com/livenews/3121232",
          "source": "华尔街见闻-快讯",
          "ranks": [
            24
          ],
          "is_new": false,
          "appearance_count": 1,
          "time_info": "05时11分"
        },
        {
          "title": "SpaceX美股盘前跌幅扩大至2%。",
          "url": "https://wallstreetcn.com/livenews/3121676",
          "source": "华尔街见闻-快讯",
          "ranks": [
            24
          ],
          "is_new": true,
          "appearance_count": 1,
          "time_info": "20时57分"
        },
        {
          "title": "哥伦比亚国家石油公司：封锁已导致超过80万桶石油无法生产。",
          "url": "https://flash.jin10.com/detail/20260618013545398800",
          "source": "金十数据",
          "ranks": [
            25
          ],
          "is_new": false,
          "appearance_count": 1,
          "time_info": "02时23分"
        },
        {
          "title": "彭博美元指数创3月13日以来最大盘中涨幅",
          "url": "https://wallstreetcn.com/livenews/3121231",
          "source": "华尔街见闻-快讯",
          "ranks": [
            25
          ],
          "is_new": false,
          "appearance_count": 1,
          "time_info": "05时11分"
        },
        {
          "title": "港股医药股拉升，恒生生物科技指数涨超3%，再鼎医药涨超7%，英矽智能、映恩生物、康方生物涨超6%。",
          "url": "https://wallstreetcn.com/livenews/3121376",
          "source": "华尔街见闻-快讯",
          "ranks": [
            26
          ],
          "is_new": false,
          "appearance_count": 1,
          "time_info": "12时15分"
        },
        {
          "title": "A股连跌5年股曝光",
          "url": "https://s.weibo.com/weibo?q=%23A%E8%82%A1%E8%BF%9E%E8%B7%8C5%E5%B9%B4%E8%82%A1%E6%9B%9D%E5%85%89%23&t=31&band_rank=26&Refer=top",
          "source": "微博",
          "ranks": [
            26
          ],
          "is_new": false,
          "appearance_count": 1,
          "time_info": "12时15分"
        },
        {
          "title": "A股医药股震荡反弹，华森制药涨停，博瑞医药、皓元医药涨超10%，众生药业、恒瑞医药、甘李药业涨幅居前。",
          "url": "https://wallstreetcn.com/livenews/3121374",
          "source": "华尔街见闻-快讯",
          "ranks": [
            27
          ],
          "is_new": false,
          "appearance_count": 1,
          "time_info": "12时15分"
        },
        {
          "title": "欧元兑美元EUR/USD日内跌幅达1.00%，现报1.1492。",
          "url": "https://flash.jin10.com/detail/20260618033047900800",
          "source": "金十数据",
          "ranks": [
            28
          ],
          "is_new": false,
          "appearance_count": 1,
          "time_info": "05时11分"
        },
        {
          "title": "两年期美债收益率于美联储利率决议日涨约13.3个基点，两年期实际收益率也在沃什首秀日涨约20个基点",
          "url": "https://wallstreetcn.com/livenews/3121268",
          "source": "华尔街见闻-快讯",
          "ranks": [
            28
          ],
          "is_new": false,
          "appearance_count": 1,
          "time_info": "07时28分"
        }
      ]
    },
    {
      "keyword_group": "外交部 商务部 证监会 央行",
      "match_count": 45,
      "titles": [
        {
          "title": "中方在美菲压力下撤出黄岩岛设施？外交部回应",
          "url": "https://news.ifeng.com/c/8u20dDE65U5",
          "source": "凤凰网",
          "ranks": [
            2
          ],
          "is_new": false,
          "appearance_count": 4,
          "time_info": "[02时23分 ~ 07时28分]"
        },
        {
          "title": "伊朗称要成为中国真正的伙伴，外交部表态",
          "url": "https://news.ifeng.com/c/8u3juhtDVpR",
          "source": "凤凰网",
          "ranks": [
            1
          ],
          "is_new": false,
          "appearance_count": 2,
          "time_info": "[20时56分 ~ 20时57分]"
        },
        {
          "title": "商务部等八部门发布《关于加快“人工智能+消费”发展的实施意见》",
          "url": "https://www.cls.cn/detail/2403573",
          "source": "财联社热门",
          "ranks": [
            4
          ],
          "is_new": false,
          "appearance_count": 2,
          "time_info": "[20时56分 ~ 20时57分]"
        },
        {
          "title": "美加强对韩日核保护，外交部：严重关切！",
          "url": "https://news.ifeng.com/c/8u3fz9phodE",
          "source": "凤凰网",
          "ranks": [
            4
          ],
          "is_new": false,
          "appearance_count": 2,
          "time_info": "[20时56分 ~ 20时57分]"
        },
        {
          "title": "伊朗外交部：伊美本周五日内瓦会谈待定",
          "url": "https://flash.jin10.com/detail/20260618072457872800",
          "source": "金十数据",
          "ranks": [
            1
          ],
          "is_new": false,
          "appearance_count": 1,
          "time_info": "07时28分"
        },
        {
          "title": "欧洲央行首席经济学家连恩：欧元升值仍对价格施加下行压力。",
          "url": "https://flash.jin10.com/detail/20260618204336557800",
          "source": "金十数据",
          "ranks": [
            2
          ],
          "is_new": true,
          "appearance_count": 1,
          "time_info": "20时57分"
        },
        {
          "title": "商务部：会同相关部门落实落细各项政策举措，持续推动人工智能与消费深度融合",
          "url": "https://wallstreetcn.com/livenews/3121577",
          "source": "华尔街见闻-快讯",
          "ranks": [
            3
          ],
          "is_new": false,
          "appearance_count": 1,
          "time_info": "17时17分"
        },
        {
          "title": "美加强对韩日核保护，外交部回应",
          "url": "https://news.ifeng.com/c/8u3fz9phodE",
          "source": "凤凰网",
          "ranks": [
            4
          ],
          "is_new": false,
          "appearance_count": 1,
          "time_info": "17时17分"
        },
        {
          "title": "欧洲央行首席经济学家连恩：我们认为，人工智能已在投资数据中显现出来。",
          "url": "https://flash.jin10.com/detail/20260618204158416800",
          "source": "金十数据",
          "ranks": [
            4
          ],
          "is_new": true,
          "appearance_count": 1,
          "time_info": "20时57分"
        },
        {
          "title": "【瑞士外交部：美伊会谈19日在比尔根山举行】瑞士外交部18日表示，美国和伊朗计划与调解方巴基斯坦、卡塔尔及其他相关国家于19日在瑞士比尔根山举行会谈，就协议的执行进行初步谈判。 瑞士外交部对媒体表示，瑞士对美国和伊朗签署谅解备忘录表示欢迎，称这是中东地区局势缓和的重要一步。（新华社）",
          "url": "https://wallstreetcn.com/livenews/3121576",
          "source": "华尔街见闻-快讯",
          "ranks": [
            4
          ],
          "is_new": false,
          "appearance_count": 1,
          "time_info": "17时17分"
        },
        {
          "title": "宣布六项政策，央行行长潘功胜详解中国金融结构变迁和金融市场现代化",
          "url": "https://m.thepaper.cn/newsDetail_forward_33397624",
          "source": "澎湃新闻",
          "ranks": [
            17,
            18
          ],
          "is_new": false,
          "appearance_count": 5,
          "time_info": "[02时23分 ~ 12时15分]"
        },
        {
          "title": "外交部：敦促日方给出一个交代",
          "url": "https://news.ifeng.com/c/8u21DLM7oTN",
          "source": "凤凰网",
          "ranks": [
            6
          ],
          "is_new": false,
          "appearance_count": 4,
          "time_info": "[02时23分 ~ 07时28分]"
        },
        {
          "title": "G7称将降低对中国关键矿产的依赖，外交部回应",
          "url": "https://www.cls.cn/detail/2403540",
          "source": "财联社热门",
          "ranks": [
            11
          ],
          "is_new": false,
          "appearance_count": 2,
          "time_info": "[20时56分 ~ 20时57分]"
        },
        {
          "title": "欧洲央行首席经济学家连恩：就业稳定，实际收入持续增长。",
          "url": "https://flash.jin10.com/detail/20260618204004881800",
          "source": "金十数据",
          "ranks": [
            7
          ],
          "is_new": true,
          "appearance_count": 1,
          "time_info": "20时57分"
        },
        {
          "title": "巴西总统卢拉：外交部、商务部官员正与美国进行谈判。",
          "url": "https://flash.jin10.com/detail/20260618014802145800",
          "source": "金十数据",
          "ranks": [
            8
          ],
          "is_new": false,
          "appearance_count": 1,
          "time_info": "02时23分"
        },
        {
          "title": "欧洲央行首席经济学家Lane：即使在较温和的情景下，加息也是合理的。 即使现在油价下跌，食品价格也会上涨。 欧洲央行加息旨在抑制价格冲击。",
          "url": "https://wallstreetcn.com/livenews/3121702",
          "source": "华尔街见闻-快讯",
          "ranks": [
            8
          ],
          "is_new": true,
          "appearance_count": 1,
          "time_info": "20时57分"
        },
        {
          "title": "欧洲央行首席经济学家连恩：欧洲央行在利率政策上采取更积极的行动，意味着更长期的稳定。",
          "url": "https://flash.jin10.com/detail/20260618203836931800",
          "source": "金十数据",
          "ranks": [
            9
          ],
          "is_new": true,
          "appearance_count": 1,
          "time_info": "20时57分"
        },
        {
          "title": "商务部等8部门：加快推出新一代人工智能手机、智能电脑等智能家居产品",
          "url": "https://wallstreetcn.com/livenews/3121699",
          "source": "华尔街见闻-快讯",
          "ranks": [
            10
          ],
          "is_new": true,
          "appearance_count": 1,
          "time_info": "20时57分"
        },
        {
          "title": "华侨银行：菲律宾和印尼央行可能收紧货币政策",
          "url": "https://flash.jin10.com/detail/20260618113021121800",
          "source": "金十数据",
          "ranks": [
            11
          ],
          "is_new": false,
          "appearance_count": 1,
          "time_info": "12时15分"
        },
        {
          "title": "欧洲央行首席经济学家连恩：我们不希望利率大幅剧烈波动。",
          "url": "https://flash.jin10.com/detail/20260618203639361800",
          "source": "金十数据",
          "ranks": [
            12
          ],
          "is_new": true,
          "appearance_count": 1,
          "time_info": "20时57分"
        },
        {
          "title": "欧洲央行首席经济学家连恩：中性利率区间的上限已升至2.5%。",
          "url": "https://flash.jin10.com/detail/20260618203615412800",
          "source": "金十数据",
          "ranks": [
            13
          ],
          "is_new": true,
          "appearance_count": 1,
          "time_info": "20时57分"
        },
        {
          "title": "伊朗外交部：与阿曼基本敲定霍尔木兹海峡管理机制",
          "url": "https://wallstreetcn.com/livenews/3121288",
          "source": "华尔街见闻-快讯",
          "ranks": [
            13
          ],
          "is_new": false,
          "appearance_count": 1,
          "time_info": "07时28分"
        },
        {
          "title": "机构：英国央行未来数月或将维持利率不变",
          "url": "https://flash.jin10.com/detail/20260618203602409800",
          "source": "金十数据",
          "ranks": [
            14
          ],
          "is_new": true,
          "appearance_count": 1,
          "time_info": "20时57分"
        },
        {
          "title": "证监会主席吴清表示，扩大第五套标准适用范围至人工智能领域，大力支持上市公司并购及再融资，透露哪些信息？",
          "url": "https://www.zhihu.com/question/2050547521164932018",
          "source": "知乎",
          "ranks": [
            15
          ],
          "is_new": false,
          "appearance_count": 1,
          "time_info": "12时15分"
        },
        {
          "title": "欧洲央行管委Kocher称伊朗协议后 通胀仍将在一段时间内维持较高水平",
          "url": "https://wallstreetcn.com/livenews/3121560",
          "source": "华尔街见闻-快讯",
          "ranks": [
            16
          ],
          "is_new": false,
          "appearance_count": 1,
          "time_info": "17时17分"
        },
        {
          "title": "英国央行利率决议今晚19:00登场",
          "url": "https://flash.jin10.com/detail/20260618170311915800",
          "source": "金十数据",
          "ranks": [
            18
          ],
          "is_new": false,
          "appearance_count": 1,
          "time_info": "17时17分"
        },
        {
          "title": "英国央行6月决议要点汇总",
          "url": "https://wallstreetcn.com/livenews/3121685",
          "source": "华尔街见闻-快讯",
          "ranks": [
            18
          ],
          "is_new": true,
          "appearance_count": 1,
          "time_info": "20时57分"
        },
        {
          "title": "伊朗外交部发言人：目前尚未确认伊朗与美国将于周五在瑞士举行会谈。",
          "url": "https://flash.jin10.com/detail/20260618064052879800",
          "source": "金十数据",
          "ranks": [
            19
          ],
          "is_new": false,
          "appearance_count": 1,
          "time_info": "07时28分"
        },
        {
          "title": "巴西央行连续三次降息，委员会Copom一致决定将基准Selic利率下调25个基点至14.25%，创2025年5月份以来新低。",
          "url": "https://wallstreetcn.com/livenews/3121280",
          "source": "华尔街见闻-快讯",
          "ranks": [
            19
          ],
          "is_new": false,
          "appearance_count": 1,
          "time_info": "07时28分"
        },
        {
          "title": "伊朗外交部发言人：伊朗和阿曼将制定海峡管理机制，必要时将与其他国家交换意见。",
          "url": "https://flash.jin10.com/detail/20260618014127425800",
          "source": "金十数据",
          "ranks": [
            20
          ],
          "is_new": false,
          "appearance_count": 1,
          "time_info": "02时23分"
        },
        {
          "title": "伊朗外交部：与阿曼基本敲定霍尔木兹海峡管理机制",
          "url": "https://flash.jin10.com/detail/20260618063743531800",
          "source": "金十数据",
          "ranks": [
            20
          ],
          "is_new": false,
          "appearance_count": 1,
          "time_info": "07时28分"
        },
        {
          "title": "欧洲央行首席经济学家连恩：我们是从坚定的中性立场开始收紧政策的。",
          "url": "https://flash.jin10.com/detail/20260618203355446800",
          "source": "金十数据",
          "ranks": [
            20
          ],
          "is_new": true,
          "appearance_count": 1,
          "time_info": "20时57分"
        },
        {
          "title": "据伊朗国家媒体：伊朗外交部发言人表示，关于霍尔木兹海峡问题，已商定在一定时间内使海上交通恢复正常。",
          "url": "https://flash.jin10.com/detail/20260618014020805800",
          "source": "金十数据",
          "ranks": [
            22
          ],
          "is_new": false,
          "appearance_count": 1,
          "time_info": "02时23分"
        },
        {
          "title": "伊朗外交部发言人：谅解备忘录于上周日已敲定，但出于标准的外交程序以及需与各方协调的重要性，所以延迟至周三才公布。",
          "url": "https://flash.jin10.com/detail/20260618063654798800",
          "source": "金十数据",
          "ranks": [
            22
          ],
          "is_new": false,
          "appearance_count": 1,
          "time_info": "07时28分"
        },
        {
          "title": "伊朗外交部发言人：谈判团队仍将出席在瑞士的会议，协议已以电子形式签署，在瑞士不会举行签署仪式。",
          "url": "https://flash.jin10.com/detail/20260618063224396800",
          "source": "金十数据",
          "ranks": [
            23
          ],
          "is_new": false,
          "appearance_count": 1,
          "time_info": "07时28分"
        },
        {
          "title": "中国人民银行、中国证监会有关部门负责人就香港近期推出5年期人民币国债期货答记者问",
          "url": "https://flash.jin10.com/detail/20260618170108358800",
          "source": "金十数据",
          "ranks": [
            23
          ],
          "is_new": false,
          "appearance_count": 1,
          "time_info": "17时17分"
        },
        {
          "title": "瑞士央行理事Tschudin：瑞士经济指标显示增长势头稳固。",
          "url": "https://wallstreetcn.com/livenews/3121545",
          "source": "华尔街见闻-快讯",
          "ranks": [
            23
          ],
          "is_new": false,
          "appearance_count": 1,
          "time_info": "17时17分"
        },
        {
          "title": "英国央行行长贝利：虽然我并不认为“脱欧”带来了积极影响，但它对英国金融业造成的损害远未达到某些人最初预期的程度。",
          "url": "https://flash.jin10.com/detail/20260618203228687800",
          "source": "金十数据",
          "ranks": [
            24
          ],
          "is_new": true,
          "appearance_count": 1,
          "time_info": "20时57分"
        },
        {
          "title": "英国央行行长贝利：稳定性很重要。",
          "url": "https://flash.jin10.com/detail/20260618203217904800",
          "source": "金十数据",
          "ranks": [
            25
          ],
          "is_new": true,
          "appearance_count": 1,
          "time_info": "20时57分"
        },
        {
          "title": "挪威央行：可能有必要进一步加息。",
          "url": "https://wallstreetcn.com/livenews/3121542",
          "source": "华尔街见闻-快讯",
          "ranks": [
            25
          ],
          "is_new": false,
          "appearance_count": 1,
          "time_info": "17时17分"
        },
        {
          "title": "欧洲央行首席经济学家连恩：欧洲经济表现良好。",
          "url": "https://flash.jin10.com/detail/20260618203141432800",
          "source": "金十数据",
          "ranks": [
            26
          ],
          "is_new": true,
          "appearance_count": 1,
          "time_info": "20时57分"
        },
        {
          "title": "瑞士央行理事Martin：预计全球通胀将保持高位。 中东局势仍然脆弱。",
          "url": "https://wallstreetcn.com/livenews/3121541",
          "source": "华尔街见闻-快讯",
          "ranks": [
            26
          ],
          "is_new": false,
          "appearance_count": 1,
          "time_info": "17时17分"
        },
        {
          "title": "瑞士央行行长Schlegel：瑞郎面临强劲升值压力的风险依然存在。 中期通胀压力几乎没有变化。 瑞士央行的货币政策继续发挥扩张性效应。 通胀率将在未来几个季度上升，随后回落。 瑞士央行已增强干预外汇市场的意愿。 尽管美伊达成和平协议，不确定性仍然高企。 能源价格仍由战局决定。 “如有必要”的意思就是“如有必要”。 很难说这是否意味着更多行动还是更少行动。 自上次决策以来，瑞郎已经贬值。 对声明措辞进行调整是适当的。 我的工作不会变得更容易，我并不觉得无聊。",
          "url": "https://wallstreetcn.com/livenews/3121538",
          "source": "华尔街见闻-快讯",
          "ranks": [
            28
          ],
          "is_new": false,
          "appearance_count": 1,
          "time_info": "17时17分"
        },
        {
          "title": "媒体调查：90%经济学家预计日本央行年底前将再次加息",
          "url": "https://wallstreetcn.com/livenews/3121265",
          "source": "华尔街见闻-快讯",
          "ranks": [
            30
          ],
          "is_new": false,
          "appearance_count": 1,
          "time_info": "07时28分"
        },
        {
          "title": "交易员维持对英国央行利率的预期不变，预计今年将加息35个基点。",
          "url": "https://wallstreetcn.com/livenews/3121669",
          "source": "华尔街见闻-快讯",
          "ranks": [
            30
          ],
          "is_new": true,
          "appearance_count": 1,
          "time_info": "20时57分"
        }
      ]
    },
    {
      "keyword_group": "DeepSeek AI openai 机器人 小米 特斯拉 英伟达",
      "match_count": 32,
      "titles": [
        {
          "title": "一天涨出一个巴菲特！AI加持，马斯克身家涨到飞起",
          "url": "https://m.thepaper.cn/newsDetail_forward_33333525",
          "source": "澎湃新闻",
          "ranks": [
            13,
            11,
            6,
            3,
            1
          ],
          "is_new": false,
          "appearance_count": 7,
          "time_info": "[05时10分 ~ 20时57分]"
        },
        {
          "title": "小米高管称数字抽真空会成为趋势，格力称空调不行抽多久真空也白扯，如何看待双方观点？双方到底在争什么？",
          "url": "https://www.zhihu.com/question/2050275486652000215",
          "source": "知乎",
          "ranks": [
            5,
            1,
            2
          ],
          "is_new": false,
          "appearance_count": 4,
          "time_info": "[02时23分 ~ 07时28分]"
        },
        {
          "title": "中国机器人开始治理沙漠了",
          "url": "https://www.baidu.com/s?wd=%E4%B8%AD%E5%9B%BD%E6%9C%BA%E5%99%A8%E4%BA%BA%E5%BC%80%E5%A7%8B%E6%B2%BB%E7%90%86%E6%B2%99%E6%BC%A0%E4%BA%86",
          "source": "百度热搜",
          "ranks": [
            3
          ],
          "is_new": false,
          "appearance_count": 4,
          "time_info": "[02时23分 ~ 07时28分]"
        },
        {
          "title": "让AI走进千家万户",
          "url": "https://www.baidu.com/s?wd=%E8%AE%A9AI%E8%B5%B0%E8%BF%9B%E5%8D%83%E5%AE%B6%E4%B8%87%E6%88%B7",
          "source": "百度热搜",
          "ranks": [
            3
          ],
          "is_new": false,
          "appearance_count": 2,
          "time_info": "[20时56分 ~ 20时57分]"
        },
        {
          "title": "悬在市场上空的“三大利空”：沃什“鹰鸽不明”，AI“武器化监管”，美股史上最大股票发行潮",
          "url": "https://wallstreetcn.com/articles/3774852",
          "source": "华尔街见闻",
          "ranks": [
            6,
            5,
            7
          ],
          "is_new": false,
          "appearance_count": 4,
          "time_info": "[02时23分 ~ 07时28分]"
        },
        {
          "title": "前5个月上海口岸机器人出口额超83亿元 规模居全国首位",
          "url": "https://flash.jin10.com/detail/20260618171258956800",
          "source": "金十数据",
          "ranks": [
            3
          ],
          "is_new": false,
          "appearance_count": 1,
          "time_info": "17时17分"
        },
        {
          "title": "如何看待 6 月 16 日 DeepSeek 网页端 /App 中的「快速模式」思维链发生明显变化？",
          "url": "https://www.zhihu.com/question/2050272536898835791",
          "source": "知乎",
          "ranks": [
            5,
            7,
            13
          ],
          "is_new": false,
          "appearance_count": 4,
          "time_info": "[12时15分 ~ 20时57分]"
        },
        {
          "title": "人开始扮演仿生机器人了",
          "url": "https://www.douyin.com/hot/2538327",
          "source": "抖音",
          "ranks": [
            23,
            16,
            19
          ],
          "is_new": false,
          "appearance_count": 5,
          "time_info": "[02时23分 ~ 12时15分]"
        },
        {
          "title": "HR 吐槽面试遇到豆包味很浓的应届生，全程依赖豆包 AI 作答，如何看待这一现象？暴露出哪些问题？",
          "url": "https://www.zhihu.com/question/2050618204980863708",
          "source": "知乎",
          "ranks": [
            6,
            7
          ],
          "is_new": false,
          "appearance_count": 4,
          "time_info": "[02时23分 ~ 07时28分]"
        },
        {
          "title": "台积电产能告急！三星代工需求火热：谷歌、英伟达、AMD都来了…",
          "url": "https://www.cls.cn/detail/2402553",
          "source": "财联社热门",
          "ranks": [
            9,
            13
          ],
          "is_new": false,
          "appearance_count": 4,
          "time_info": "[02时23分 ~ 07时28分]"
        },
        {
          "title": "SpaceX 上市第三天市值逼近 3 万亿美元，豪掷 600 亿收购 Cursor 加码 AI，这笔天价收购划算吗？",
          "url": "https://www.zhihu.com/question/2050515273640423854",
          "source": "知乎",
          "ranks": [
            17,
            16
          ],
          "is_new": false,
          "appearance_count": 4,
          "time_info": "[02时23分 ~ 07时28分]"
        },
        {
          "title": "AI内存极限再创突破！SK海力士宣布交付12层HBM4E样品",
          "url": "https://www.cls.cn/detail/2403255",
          "source": "财联社热门",
          "ranks": [
            13,
            8
          ],
          "is_new": false,
          "appearance_count": 3,
          "time_info": "[17时17分 ~ 20时57分]"
        },
        {
          "title": "小米空调10年免费加氟",
          "url": "https://s.weibo.com/weibo?q=%23%E5%B0%8F%E7%B1%B3%E7%A9%BA%E8%B0%8310%E5%B9%B4%E5%85%8D%E8%B4%B9%E5%8A%A0%E6%B0%9F%23&t=31&band_rank=10&Refer=top",
          "source": "微博",
          "ranks": [
            10,
            19
          ],
          "is_new": false,
          "appearance_count": 3,
          "time_info": "[17时17分 ~ 20时57分]"
        },
        {
          "title": "用AI打开端午的一百种方式",
          "url": "https://www.douyin.com/hot/2539388",
          "source": "抖音",
          "ranks": [
            10,
            12
          ],
          "is_new": false,
          "appearance_count": 3,
          "time_info": "[17时17分 ~ 20时57分]"
        },
        {
          "title": "如果我们生活在 AI 构建的虚拟世界里，随手抛一枚均匀硬币，正面朝上的概率还是现实中公认的「50%」吗？",
          "url": "https://www.zhihu.com/question/2050269478747889665",
          "source": "知乎",
          "ranks": [
            10,
            14
          ],
          "is_new": false,
          "appearance_count": 3,
          "time_info": "[02时23分 ~ 05时11分]"
        },
        {
          "title": "如何理解韩国作家金爱烂所说的：「人类拥有而 AI 没有的一样东西，是犹豫不决」？",
          "url": "https://www.zhihu.com/question/2046913494243435264",
          "source": "知乎",
          "ranks": [
            12
          ],
          "is_new": false,
          "appearance_count": 3,
          "time_info": "[02时23分 ~ 05时11分]"
        },
        {
          "title": "为什么 AI 写的代码没人说有 AI 味儿，但是 AI 写的文章就一眼看出 AI 味儿？",
          "url": "https://www.zhihu.com/question/14853864339",
          "source": "知乎",
          "ranks": [
            8
          ],
          "is_new": false,
          "appearance_count": 2,
          "time_info": "[12时15分 ~ 17时17分]"
        },
        {
          "title": "黄金和AI：谁在见顶？",
          "url": "https://wallstreetcn.com/articles/3774914",
          "source": "华尔街见闻",
          "ranks": [
            10,
            7
          ],
          "is_new": false,
          "appearance_count": 2,
          "time_info": "[12时15分 ~ 17时17分]"
        },
        {
          "title": "【每日收评】科创50放量涨近4%，AI硬件与半导体持续火爆，多只科技权重续创历史新高",
          "url": "https://www.cls.cn/detail/2403645",
          "source": "财联社热门",
          "ranks": [
            12
          ],
          "is_new": false,
          "appearance_count": 2,
          "time_info": "[20时56分 ~ 20时57分]"
        },
        {
          "title": "吴清陆家嘴论坛讲话：扩大第五套标准适用范围至AI领域，支持港股公司境内上市",
          "url": "https://wallstreetcn.com/articles/3774870",
          "source": "华尔街见闻",
          "ranks": [
            8
          ],
          "is_new": false,
          "appearance_count": 1,
          "time_info": "12时15分"
        },
        {
          "title": "【每日收评】科创50低开高走涨超4.5%，AI硬件反复活跃，半导体产业链再迎爆发",
          "url": "https://www.cls.cn/detail/2402436",
          "source": "财联社热门",
          "ranks": [
            8
          ],
          "is_new": false,
          "appearance_count": 1,
          "time_info": "02时23分"
        },
        {
          "title": "AirPods五大升级",
          "url": "https://s.weibo.com/weibo?q=%23AirPods%E4%BA%94%E5%A4%A7%E5%8D%87%E7%BA%A7%23&t=31&band_rank=10&Refer=top",
          "source": "微博",
          "ranks": [
            10
          ],
          "is_new": false,
          "appearance_count": 1,
          "time_info": "12时15分"
        },
        {
          "title": "阿里巴巴集团：阿里云计划在2026年下半年在马来西亚和欧洲市场推出一系列智能AI服务。",
          "url": "https://flash.jin10.com/detail/20260618170737641800",
          "source": "金十数据",
          "ranks": [
            12
          ],
          "is_new": false,
          "appearance_count": 1,
          "time_info": "17时17分"
        },
        {
          "title": "下半年投资亮点纷呈，公募策略会看好AI投资范式生变",
          "url": "https://wallstreetcn.com/livenews/3121289",
          "source": "华尔街见闻-快讯",
          "ranks": [
            12
          ],
          "is_new": false,
          "appearance_count": 1,
          "time_info": "07时28分"
        },
        {
          "title": "黄仁勋呼吁全民拥抱AI：社会需重塑规则体系 能源短缺成美国AI发展最大短板",
          "url": "https://www.cls.cn/detail/2402612",
          "source": "财联社热门",
          "ranks": [
            13
          ],
          "is_new": false,
          "appearance_count": 1,
          "time_info": "02时23分"
        },
        {
          "title": "苹果(AAPL.O)正在为2027年春季发布第二代iPhone Air做准备。iPhone Air原型机将配备第二后置摄像头并升级电池。",
          "url": "https://flash.jin10.com/detail/20260618035839383800",
          "source": "金十数据",
          "ranks": [
            14
          ],
          "is_new": false,
          "appearance_count": 1,
          "time_info": "05时11分"
        },
        {
          "title": "OpenAI的CEO Altman、谷歌公司高管Hassabis、Anthropic的CEO Amodei、Meta高管Wang、Mistral AI高管Mensch、Cohere高管Gomez、Salesforce高管Benioff出席（美国）AI会议。（Axios）",
          "url": "https://wallstreetcn.com/livenews/3121165",
          "source": "华尔街见闻-快讯",
          "ranks": [
            14
          ],
          "is_new": false,
          "appearance_count": 1,
          "time_info": "02时23分"
        },
        {
          "title": "苹果筹备第二代iPhone Air，预计2027年春季推出",
          "url": "https://wallstreetcn.com/livenews/3121243",
          "source": "华尔街见闻-快讯",
          "ranks": [
            14
          ],
          "is_new": false,
          "appearance_count": 1,
          "time_info": "05时11分"
        },
        {
          "title": "AI Agent 的核心技术是什么？",
          "url": "https://www.zhihu.com/question/1906023807417811104",
          "source": "知乎",
          "ranks": [
            19
          ],
          "is_new": false,
          "appearance_count": 1,
          "time_info": "02时23分"
        },
        {
          "title": "iPhoneAir2爆料汇总",
          "url": "https://s.weibo.com/weibo?q=%23iPhoneAir2%E7%88%86%E6%96%99%E6%B1%87%E6%80%BB%23&t=31&band_rank=20&Refer=top",
          "source": "微博",
          "ranks": [
            20
          ],
          "is_new": false,
          "appearance_count": 1,
          "time_info": "12时15分"
        },
        {
          "title": "美国总统特朗普：围绕经济、AI举行了一些不错的会议。",
          "url": "https://wallstreetcn.com/livenews/3121153",
          "source": "华尔街见闻-快讯",
          "ranks": [
            23
          ],
          "is_new": false,
          "appearance_count": 1,
          "time_info": "02时23分"
        },
        {
          "title": "端午和周星驰拍上AI食神大片了",
          "url": "https://www.douyin.com/hot/2538982",
          "source": "抖音",
          "ranks": [
            29
          ],
          "is_new": false,
          "appearance_count": 1,
          "time_info": "17时17分"
        }
      ]
    },
    {
      "keyword_group": "黄金 白银 铜 铝 稀土",
      "match_count": 24,
      "titles": [
        {
          "title": "美联储鹰派转向，美股债遭“双杀”，SpaceX首度收跌，芯片指数逆市收涨，黄金下挫",
          "url": "https://wallstreetcn.com/articles/3774887",
          "source": "华尔街见闻",
          "ranks": [
            2,
            1
          ],
          "is_new": false,
          "appearance_count": 5,
          "time_info": "[07时28分 ~ 20时57分]"
        },
        {
          "title": "香港机场发生黄金大劫案",
          "url": "https://s.weibo.com/weibo?q=%23%E9%A6%99%E6%B8%AF%E6%9C%BA%E5%9C%BA%E5%8F%91%E7%94%9F%E9%BB%84%E9%87%91%E5%A4%A7%E5%8A%AB%E6%A1%88%23&t=31&band_rank=1&Refer=top",
          "source": "微博",
          "ranks": [
            1
          ],
          "is_new": false,
          "appearance_count": 2,
          "time_info": "[20时56分 ~ 20时57分]"
        },
        {
          "title": "日本焚烧炉中炼出7000多克黄金",
          "url": "https://www.toutiao.com/trending/7652597493637283894/",
          "source": "今日头条",
          "ranks": [
            4
          ],
          "is_new": false,
          "appearance_count": 2,
          "time_info": "[20时56分 ~ 20时57分]"
        },
        {
          "title": "美联储决议声明发布前，标普500指数大致持平，道指涨0.3%，纳指涨0.2%，半导体指数涨3.6%，银行指数涨1.3%。 美元指数涨0.1%，美元兑日元跌0.16%，欧元兑美元跌0.1%，英镑兑美元跌0.2%。 现货黄金涨1.1%，白银涨1.8%。 美国10年期国债收益率跌1.38个基点，报4.4256%，两年期美债收益率涨幅收窄至不足0.5个基点。",
          "url": "https://wallstreetcn.com/livenews/3121179",
          "source": "华尔街见闻-快讯",
          "ranks": [
            1
          ],
          "is_new": false,
          "appearance_count": 1,
          "time_info": "02时23分"
        },
        {
          "title": "高市称担心中国稀土限制 中方回应",
          "url": "https://www.toutiao.com/trending/7651865585030316038/",
          "source": "今日头条",
          "ranks": [
            2
          ],
          "is_new": false,
          "appearance_count": 1,
          "time_info": "17时17分"
        },
        {
          "title": "【早报】美联储转鹰；美股三大指数集体收跌；黄金、白银下跌；葡萄牙队爆冷战平",
          "url": "https://www.cls.cn/detail/2403010",
          "source": "财联社热门",
          "ranks": [
            2
          ],
          "is_new": false,
          "appearance_count": 1,
          "time_info": "12时15分"
        },
        {
          "title": "现货白银日内涨幅达2.0%，报71.49美元/盎司。",
          "url": "https://wallstreetcn.com/livenews/3121176",
          "source": "华尔街见闻-快讯",
          "ranks": [
            4
          ],
          "is_new": false,
          "appearance_count": 1,
          "time_info": "02时23分"
        },
        {
          "title": "沃什“首秀”美联储放鹰，三大美股指转跌，美元拉升，美债黄金跳水",
          "url": "https://wallstreetcn.com/articles/3774939",
          "source": "华尔街见闻",
          "ranks": [
            9,
            8
          ],
          "is_new": false,
          "appearance_count": 4,
          "time_info": "[12时15分 ~ 20时57分]"
        },
        {
          "title": "风险偏好重燃，美股盘前半导体股大涨，英特尔涨近9%，日元创近两年新低，黄金向上触及4300美元",
          "url": "https://wallstreetcn.com/articles/3774963",
          "source": "华尔街见闻",
          "ranks": [
            6
          ],
          "is_new": false,
          "appearance_count": 2,
          "time_info": "[20时56分 ~ 20时57分]"
        },
        {
          "title": "你买空调会在意铝制还是铜制吗",
          "url": "https://s.weibo.com/weibo?q=%23%E4%BD%A0%E4%B9%B0%E7%A9%BA%E8%B0%83%E4%BC%9A%E5%9C%A8%E6%84%8F%E9%93%9D%E5%88%B6%E8%BF%98%E6%98%AF%E9%93%9C%E5%88%B6%E5%90%97%23&t=31&band_rank=30&Refer=top",
          "source": "微博",
          "ranks": [
            30
          ],
          "is_new": false,
          "appearance_count": 2,
          "time_info": "[20时56分 ~ 20时57分]"
        },
        {
          "title": "地产ETF收跌2.5%，与黄金ETF领跌美国大类资产类ETF",
          "url": "https://wallstreetcn.com/livenews/3121253",
          "source": "华尔街见闻-快讯",
          "ranks": [
            6
          ],
          "is_new": false,
          "appearance_count": 1,
          "time_info": "05时11分"
        },
        {
          "title": "技术刘Pro：美联储鹰派点阵图与美伊协议拉锯，黄金重返低点附近考验支撑",
          "url": "https://flash.jin10.com/detail/20260618203650841800",
          "source": "金十数据",
          "ranks": [
            11
          ],
          "is_new": true,
          "appearance_count": 1,
          "time_info": "20时57分"
        },
        {
          "title": "国际铜夜盘收涨0.25%，沪铜收涨0.21%，沪铝收涨0.21%，沪锌收涨0.67%，沪铅收涨0.27%，沪镍收涨0.60%，沪锡收涨0.21%。 氧化铝夜盘收涨0.52%，铝合金收涨0.17%。 不锈钢夜盘收跌0.59%。",
          "url": "https://wallstreetcn.com/livenews/3121166",
          "source": "华尔街见闻-快讯",
          "ranks": [
            13
          ],
          "is_new": false,
          "appearance_count": 1,
          "time_info": "02时23分"
        },
        {
          "title": "中国5月份氧化铝出口28万吨，同比增36.4%；1-5月累计氧化铝出口134万吨，同比增14.7%。 5月份未锻轧铝及铝材进口30万吨，同比降15.6%；1-5月累计未锻轧铝及铝材进口162万吨，同比降2.9%。 5月份钢材进口45万吨，同比降6.9%；1-5月累计钢材进口225万吨，同比降12.2%。 5月份铝矿砂及其精矿进口2,303万吨，同比增31.9%；1-5月累计铝矿砂及其精矿进口10,069万吨，同比增18.5%。",
          "url": "https://wallstreetcn.com/livenews/3121386",
          "source": "华尔街见闻-快讯",
          "ranks": [
            16
          ],
          "is_new": false,
          "appearance_count": 1,
          "time_info": "12时15分"
        },
        {
          "title": "中国5月份稀土及其制品出口10,905吨，同比增36.6%；1-5月累计稀土及其制品出口54,976吨，同比增14.9%。",
          "url": "https://wallstreetcn.com/livenews/3121385",
          "source": "华尔街见闻-快讯",
          "ranks": [
            17
          ],
          "is_new": false,
          "appearance_count": 1,
          "time_info": "12时15分"
        },
        {
          "title": "LME期铜收涨40美元，报13814美元/吨。 LME期铝收涨22美元，报3410美元/吨。 LME期锌收涨19美元，报3588美元/吨。 LME期铅收跌3美元，报1979美元/吨。 LME期镍收涨64美元，报18060美元/吨。 LME期锡收涨218美元，报55344美元/吨。 LME期钴收平，报56290美元/吨。",
          "url": "https://wallstreetcn.com/livenews/3121160",
          "source": "华尔街见闻-快讯",
          "ranks": [
            18
          ],
          "is_new": false,
          "appearance_count": 1,
          "time_info": "02时23分"
        },
        {
          "title": "现货白银日内涨超2.00%，现报71.42美元/盎司。",
          "url": "https://flash.jin10.com/detail/20260618014305229800",
          "source": "金十数据",
          "ranks": [
            19
          ],
          "is_new": false,
          "appearance_count": 1,
          "time_info": "02时23分"
        },
        {
          "title": "欧元兑美元跌超1%，刷新日低至1.1483。 澳元兑美元跌1%，刷新日低至0.6995。 现货白银日内跌幅达4.5%，报66.83美元/盎司；纽约银日内跌幅达4.5%，报67.36美元/盎司。",
          "url": "https://wallstreetcn.com/livenews/3121237",
          "source": "华尔街见闻-快讯",
          "ranks": [
            19
          ],
          "is_new": false,
          "appearance_count": 1,
          "time_info": "05时11分"
        },
        {
          "title": "现货白银日内跌幅达1.5%，报66.73美元/盎司。",
          "url": "https://wallstreetcn.com/livenews/3121683",
          "source": "华尔街见闻-快讯",
          "ranks": [
            19
          ],
          "is_new": true,
          "appearance_count": 1,
          "time_info": "20时57分"
        },
        {
          "title": "现货白银跌破67美元/盎司，日内跌4.32%。",
          "url": "https://flash.jin10.com/detail/20260618033904783800",
          "source": "金十数据",
          "ranks": [
            21
          ],
          "is_new": false,
          "appearance_count": 1,
          "time_info": "05时11分"
        },
        {
          "title": "沃什首秀放鹰，黄金何去何从？震荡格局没有改变？金十研究员Steven正在直播，立即观看>><font class=\"important-text\"></font>",
          "url": "https://flash.jin10.com/detail/20260618203354268800",
          "source": "金十数据",
          "ranks": [
            21
          ],
          "is_new": true,
          "appearance_count": 1,
          "time_info": "20时57分"
        },
        {
          "title": "现货黄金日内涨超1.00%，现报4374.60美元/盎司。",
          "url": "https://flash.jin10.com/detail/20260618013356076800",
          "source": "金十数据",
          "ranks": [
            26
          ],
          "is_new": false,
          "appearance_count": 1,
          "time_info": "02时23分"
        },
        {
          "title": "香港一男子在机场遭伏击后被抢黄金",
          "url": "https://www.toutiao.com/trending/7651537707392188422/",
          "source": "今日头条",
          "ranks": [
            28
          ],
          "is_new": false,
          "appearance_count": 1,
          "time_info": "17时17分"
        },
        {
          "title": "现货黄金日内跌幅达2.0%，报4242.32美元/盎司。 纽约金日内跌幅达2.0%，报4264.1美元/盎司。 现货白银日内跌幅达2.5%，报68.25美元/盎司。",
          "url": "https://wallstreetcn.com/livenews/3121228",
          "source": "华尔街见闻-快讯",
          "ranks": [
            28
          ],
          "is_new": false,
          "appearance_count": 1,
          "time_info": "05时11分"
        }
      ]
    }
  ],
  "report_image_url": "https://youngchampion.github.io/hotspot/img/news.jpg"
}